aioboto3/__init__.py
aioboto3/_version.py
aioboto3/session.py
aioboto3/dynamodb/__init__.py
aioboto3/dynamodb/table.py
aioboto3/experimental/__init__.py
aioboto3/experimental/async_chalice.py
aioboto3/resources/__init__.py
aioboto3/resources/action.py
aioboto3/resources/base.py
aioboto3/resources/collection.py
aioboto3/resources/factory.py
aioboto3/resources/response.py
aioboto3/s3/__init__.py
aioboto3/s3/cse.py
aioboto3/s3/inject.py
aioboto3-15.3.0.dist-info/licenses/LICENSE
aioboto3-15.3.0.dist-info/METADATA
aioboto3-15.3.0.dist-info/WHEEL
aioboto3-15.3.0.dist-info/top_level.txt
aioboto3-15.3.0.dist-info/RECORD
