Metadata-Version: 2.4
Name: aioboto3
Version: 15.3.0
Summary: Async boto3 wrapper
Author-email: Terri Cain <terri@dolphincorp.co.uk>
License: Apache-2.0
Project-URL: homepage, https://github.com/terricain/aioboto3
Project-URL: repository, https://github.com/terricain/aioboto3
Project-URL: documentation, https://readthedocs.org/projects/aioboto3/
Keywords: aioboto3,boto3,aws
Classifier: Development Status :: 5 - Production/Stable
Classifier: Intended Audience :: Developers
Classifier: License :: OSI Approved :: Apache Software License
Classifier: Natural Language :: English
Classifier: Programming Language :: Python :: 3
Classifier: Programming Language :: Python :: 3.9
Classifier: Programming Language :: Python :: 3.10
Classifier: Programming Language :: Python :: 3.11
Classifier: Programming Language :: Python :: 3.12
Classifier: Programming Language :: Python :: 3.13
Classifier: Programming Language :: Python :: 3.14
Requires-Python: >=3.9
License-File: LICENSE
Requires-Dist: aiobotocore[boto3]==2.24.3
Requires-Dist: aiofiles>=23.2.1
Provides-Extra: s3cse
Requires-Dist: cryptography>=44.0.1; extra == "s3cse"
Provides-Extra: chalice
Requires-Dist: chalice>=1.24.0; extra == "chalice"
Dynamic: license-file
